interface_relationship_manager/__init__.py
interface_relationship_manager/models.py
interface_relationship_manager/navigation.py
interface_relationship_manager/urls.py
interface_relationship_manager/utils.py
interface_relationship_manager/views.py
interface_relationship_manager/migrations/0001_initial.py
interface_relationship_manager/migrations/__init__.py
interface_relationship_manager/templates/interface_relationship_manager/select_device.html
interface_relationship_manager-1.3.1.dist-info/licenses/LICENSE
interface_relationship_manager-1.3.1.dist-info/METADATA
interface_relationship_manager-1.3.1.dist-info/WHEEL
interface_relationship_manager-1.3.1.dist-info/top_level.txt
interface_relationship_manager-1.3.1.dist-info/RECORD
