Metadata-Version: 2.4
Name: interface_relationship_manager
Version: 1.3.1
Summary: Netbox plugin for splitting interface.
Author-email: Viktor Kubec <Viktor.Kubec@gmail.com>
License-Expression: MIT
Classifier: Programming Language :: Python :: 3
Classifier: Operating System :: OS Independent
Requires-Python: >=3.8
License-File: LICENSE
Dynamic: license-file
